tencentcloud/__init__.py
tencentcloud/tbp/__init__.py
tencentcloud/tbp/v20190311/__init__.py
tencentcloud/tbp/v20190311/errorcodes.py
tencentcloud/tbp/v20190311/models.py
tencentcloud/tbp/v20190311/tbp_client.py
tencentcloud/tbp/v20190627/__init__.py
tencentcloud/tbp/v20190627/errorcodes.py
tencentcloud/tbp/v20190627/models.py
tencentcloud/tbp/v20190627/tbp_client.py
tencentcloud_sdk_python_tbp-3.0.1459.dist-info/METADATA
tencentcloud_sdk_python_tbp-3.0.1459.dist-info/WHEEL
tencentcloud_sdk_python_tbp-3.0.1459.dist-info/top_level.txt
tencentcloud_sdk_python_tbp-3.0.1459.dist-info/RECORD
